{
  "name": "baseline_imagenet",
  "model_name": "Baseline_ResNet50",
  "depth": 50,
  "dataset": "imagenet",
  "results": {
    "best_acc": 0.75858,
    "best_top1": 75.858,
    "best_top5": 92.924,
    "best_epoch": 59,
    "final_top1": 75.85,
    "final_top5": 92.946,
    "history": {
      "train_loss": [
        5.731044,
        4.188432,
        3.41295,
        3.04972,
        2.879417,
        2.702119,
        2.598529,
        2.524975,
        2.466969,
        2.422149,
        2.386514,
        2.355161,
        2.327852,
        2.304051,
        2.280279,
        2.258809,
        2.242863,
        2.221621,
        2.202679,
        2.183723,
        2.164968,
        2.143638,
        2.122352,
        2.106159,
        2.083873,
        2.062492,
        2.040203,
        2.022384,
        1.995733,
        1.976797,
        1.951838,
        1.927739,
        1.897956,
        1.872316,
        1.846397,
        1.819693,
        1.78653,
        1.760128,
        1.728526,
        1.694316,
        1.661896,
        1.627999,
        1.593044,
        1.556426,
        1.517613,
        1.477064,
        1.435429,
        1.39121,
        1.348444,
        1.303734,
        1.259513,
        1.217225,
        1.16889,
        1.125648,
        1.084967,
        1.046459,
        1.014351,
        0.993331,
        0.973447,
        0.966297
      ],
      "train_top1": [
        5.0212,
        18.6188,
        29.5517,
        35.2914,
        38.1469,
        41.2469,
        43.0928,
        44.4928,
        45.4781,
        46.3859,
        46.9723,
        47.5939,
        48.0852,
        48.5555,
        49.0262,
        49.4084,
        49.702,
        50.1197,
        50.507,
        50.8311,
        51.1944,
        51.6664,
        52.0303,
        52.314,
        52.8194,
        53.2147,
        53.5969,
        54.0349,
        54.4971,
        54.8902,
        55.36,
        55.8741,
        56.4482,
        56.9993,
        57.4736,
        58.0294,
        58.76,
        59.2371,
        59.8737,
        60.6078,
        61.2984,
        61.9735,
        62.6961,
        63.4991,
        64.3068,
        65.1839,
        66.0488,
        66.9829,
        67.9278,
        68.8961,
        69.8753,
        70.8201,
        71.8745,
        72.8254,
        73.7828,
        74.6729,
        75.3818,
        75.8766,
        76.3652,
        76.5645
      ],
      "train_top5": [
        13.9798,
        39.2682,
        53.8497,
        60.5277,
        63.6151,
        66.627,
        68.4076,
        69.6303,
        70.6066,
        71.3393,
        71.9157,
        72.4223,
        72.88,
        73.2345,
        73.6151,
        73.9572,
        74.1383,
        74.5862,
        74.8602,
        75.1603,
        75.4465,
        75.7959,
        76.1075,
        76.2942,
        76.6256,
        76.9673,
        77.3025,
        77.5875,
        77.9714,
        78.2815,
        78.5986,
        78.9615,
        79.3893,
        79.7475,
        80.1652,
        80.5328,
        81.0025,
        81.4068,
        81.8102,
        82.3074,
        82.7772,
        83.239,
        83.709,
        84.2096,
        84.734,
        85.274,
        85.8241,
        86.3917,
        86.956,
        87.4934,
        88.0629,
        88.573,
        89.1785,
        89.684,
        90.17,
        90.5862,
        90.9736,
        91.2039,
        91.4119,
        91.4993
      ],
      "val_loss": [
        5.316299,
        3.729905,
        2.967231,
        2.744123,
        2.650737,
        2.461554,
        2.599528,
        2.375731,
        2.327186,
        2.489761,
        2.327476,
        2.216545,
        2.25226,
        2.071555,
        2.13968,
        2.150113,
        2.172797,
        2.002093,
        2.131507,
        2.185508,
        2.678625,
        2.037469,
        1.959518,
        2.036454,
        2.084262,
        1.975905,
        1.803772,
        1.852622,
        1.765676,
        1.795125,
        1.91576,
        1.766153,
        1.659236,
        1.603406,
        1.622485,
        1.679814,
        1.573904,
        1.584716,
        1.52175,
        1.499019,
        1.47168,
        1.499815,
        1.431617,
        1.376771,
        1.411778,
        1.281982,
        1.24653,
        1.234706,
        1.171309,
        1.146152,
        1.119253,
        1.082596,
        1.07094,
        1.04611,
        1.000278,
        0.979645,
        0.963371,
        0.952585,
        0.946156,
        0.943983
      ],
      "val_top1": [
        11.206,
        23.488,
        35.058,
        38.922,
        40.64,
        44.184,
        41.858,
        45.75,
        46.916,
        43.954,
        46.766,
        48.78,
        48.366,
        51.414,
        50.532,
        50.236,
        49.362,
        52.862,
        50.134,
        49.906,
        42.946,
        52.394,
        54.142,
        52.31,
        51.864,
        53.818,
        57.0,
        56.044,
        57.458,
        57.108,
        55.268,
        57.888,
        59.886,
        60.838,
        60.652,
        59.47,
        62.036,
        61.492,
        62.808,
        63.456,
        64.056,
        63.622,
        65.136,
        65.924,
        65.196,
        68.004,
        69.024,
        69.074,
        70.524,
        71.14,
        71.73,
        72.598,
        73.008,
        73.544,
        74.484,
        75.15,
        75.392,
        75.702,
        75.858,
        75.85
      ],
      "val_top5": [
        27.994,
        47.304,
        61.78,
        65.478,
        67.524,
        70.784,
        69.066,
        72.37,
        73.286,
        70.646,
        73.35,
        74.968,
        74.586,
        77.578,
        76.548,
        76.168,
        76.07,
        78.58,
        76.34,
        75.6,
        68.778,
        77.944,
        79.322,
        77.926,
        77.168,
        78.89,
        81.588,
        80.932,
        82.182,
        81.638,
        79.59,
        81.922,
        83.63,
        84.374,
        84.056,
        83.418,
        84.87,
        84.538,
        85.76,
        85.794,
        86.306,
        85.776,
        86.874,
        87.454,
        86.996,
        88.77,
        89.138,
        89.332,
        90.232,
        90.414,
        90.758,
        91.332,
        91.44,
        91.636,
        92.282,
        92.478,
        92.68,
        92.89,
        92.924,
        92.946
      ],
      "lr": [
        0.08000000000000002,
        0.12,
        0.16000000000000003,
        0.2,
        0.2,
        0.19983691039261356,
        0.199348173534855,
        0.1985353835847693,
        0.19740119169423337,
        0.19594929736144975,
        0.1941844363639525,
        0.192112365311485,
        0.18973984286913584,
        0.18707460771197773,
        0.18412535328311813,
        0.18090169943749476,
        0.17741416106390828,
        0.1736741137876405,
        0.16969375686552937,
        0.16548607339452853,
        0.16106478796354384,
        0.15644432188667695,
        0.1516397461638962,
        0.14666673232256738,
        0.14154150130018867,
        0.1362807705350641,
        0.13090169943749475,
        0.12542183341934873,
        0.11985904666457455,
        0.11423148382732853,
        0.10855750084788399,
        0.10285560507936962,
        0.09714439492063039,
        0.09144249915211605,
        0.0857685161726715,
        0.08014095333542548,
        0.07457816658065133,
        0.06909830056250527,
        0.06371922946493591,
        0.05845849869981137,
        0.05333326767743263,
        0.04836025383610382,
        0.04355567811332311,
        0.03893521203645618,
        0.0345139266054715,
        0.030306243134470667,
        0.026325886212359498,
        0.022585838936091753,
        0.019098300562505267,
        0.01587464671688187,
        0.012925392288022298,
        0.01026015713086418,
        0.007887634688515,
        0.005815563636047539,
        0.004050702638550274,
        0.0025988083057666535,
        0.0014646164152307018,
        0.000651826465144978,
        0.0001630896073864352,
        0.0
      ],
      "alpha_stats": []
    },
    "elapsed_time": 55039.96,
    "alpha_final": null
  },
  "config": {
    "epochs": 60,
    "batch_size": 512,
    "lr": 0.2,
    "momentum": 0.9,
    "weight_decay": 0.0001,
    "warmup_epochs": 5,
    "amp": true,
    "seed": 42
  },
  "timestamp": "2026-03-13 06:28:05"
}